easys_ordermanager/__init__.py
easys_ordermanager/fields.py
easys_ordermanager/validators.py
easys_ordermanager/__pycache__/__init__.cpython-314.pyc
easys_ordermanager/locale/de/LC_MESSAGES/django.po
easys_ordermanager/v1/__init__.py
easys_ordermanager/v1/serializer.py
easys_ordermanager/v2/__init__.py
easys_ordermanager/v2/serializer.py
easys_ordermanager/v3/__init__.py
easys_ordermanager/v3/serializer.py
easys_ordermanager-4.1.0.dist-info/licenses/LICENSE
example/__init__.py
example/apps.py
example/settings.py
example/management/__init__.py
example/management/commands/__init__.py
example/management/commands/i18n.py
tests/__init__.py
tests/v1/__init__.py
tests/v1/test_serializer.py
tests/v2/__init__.py
tests/v2/test_serializer.py
tests/v3/__init__.py
tests/v3/test_serializer.py
easys_ordermanager-4.1.0.dist-info/METADATA
easys_ordermanager-4.1.0.dist-info/WHEEL
easys_ordermanager-4.1.0.dist-info/top_level.txt
easys_ordermanager-4.1.0.dist-info/RECORD
