Metadata-Version: 2.4
Name: easys-ordermanager
Version: 4.1.0
Summary: API definition of RH order manager for EasyS
Home-page: https://gitlab.herocentral.de/development/easys-ordermanager
Download-URL: 
Author: RegioHelden developers
Author-email: opensource@regiohelden.de
License: MIT
Requires-Python: >=3.11
License-File: LICENSE
Requires-Dist: django<6.0,>=5.2
Requires-Dist: django-countries<9.0.0,>=7.6.1
Requires-Dist: django-internationalflavor<0.5.0,>=0.4.3
Requires-Dist: django-model-utils<6.0.0,>=5.0.0
Requires-Dist: django-phonenumber-field<9.0.0,>=8.0.0
Requires-Dist: djangorestframework<3.17,>=3.16
Requires-Dist: idna<4.0,>=3.11
Requires-Dist: phonenumbers<10.0.0,>=9.0.0
Dynamic: author
Dynamic: author-email
Dynamic: description
Dynamic: description-content-type
Dynamic: home-page
Dynamic: license
Dynamic: license-file
Dynamic: requires-dist
Dynamic: summary
